alipy/__init__.py
alipy/toolbox.py
alipy/data_manipulate/__init__.py
alipy/data_manipulate/al_split.py
alipy/data_manipulate/datapreprocess.py
alipy/experiment/__init__.py
alipy/experiment/al_experiment.py
alipy/experiment/experiment_analyser.py
alipy/experiment/state.py
alipy/experiment/state_io.py
alipy/experiment/stopping_criteria.py
alipy/index/__init__.py
alipy/index/index_collections.py
alipy/index/multi_label_tools.py
alipy/metrics/__init__.py
alipy/metrics/performance.py
alipy/oracle/__init__.py
alipy/oracle/knowledge_repository.py
alipy/oracle/oracle.py
alipy/query_strategy/__init__.py
alipy/query_strategy/base.py
alipy/query_strategy/cost_sensitive.py
alipy/query_strategy/multi_label.py
alipy/query_strategy/noisy_oracles.py
alipy/query_strategy/query_features.py
alipy/query_strategy/query_labels.py
alipy/query_strategy/query_type.py
alipy/utils/__init__.py
alipy/utils/ace_warnings.py
alipy/utils/interface.py
alipy/utils/misc.py
alipy/utils/multi_thread.py
alipy-1.2.5.dist-info/LICENSE
alipy-1.2.5.dist-info/METADATA
alipy-1.2.5.dist-info/WHEEL
alipy-1.2.5.dist-info/top_level.txt
alipy-1.2.5.dist-info/RECORD
