Metadata-Version: 2.1
Name: alipy
Version: 1.2.5
Summary: Active Learning in Python
Home-page: https://github.com/NUAA-AL/ALiPy
Author: Ying-Peng Tang, Guo-Xiang Li, Sheng-Jun Huang
Author-email: tangyp@nuaa.edu.cn, GuoXiangLi@nuaa.edu.cn, huangsj@nuaa.edu.cn
License: UNKNOWN
Platform: UNKNOWN
Requires-Dist: numpy
Requires-Dist: scipy
Requires-Dist: scikit-learn
Requires-Dist: matplotlib
Requires-Dist: prettytable
